winvers/__init__.py
winvers/constants.py
winvers/util.py
winvers/winver.py
winvers-0.1.6.dist-info/LICENSE
winvers-0.1.6.dist-info/METADATA
winvers-0.1.6.dist-info/WHEEL
winvers-0.1.6.dist-info/top_level.txt
winvers-0.1.6.dist-info/RECORD
