Metadata-Version: 2.1
Name: winvers
Version: 0.1.6
Summary: Definitive Windows version checker for Python
Home-page: https://github.com/MagicGreenDragon/winver
Author: Daniele Giudice
License: GPL v3
Keywords: windows,version,check
Platform: UNKNOWN
Classifier: Development Status :: 5 - Production/Stable
Classifier: Intended Audience :: Developers
Classifier: Natural Language :: English
Classifier: License :: OSI Approved :: GNU General Public License v3 or later (GPLv3+)
Classifier: Programming Language :: Python :: 2.7
Classifier: Programming Language :: Python :: 3
Requires-Python: >=2.7, <4
